{
  "generated_at": "2026-07-03T12:55:42.590990+00:00",
  "phase": 1,
  "item_count": 21,
  "items": [
    {
      "id": "mastodon_116854065876320627",
      "source": "Mastodon #hamradio",
      "title": "Interesting, just contacted the youngest person I've ever talked to on CW (Morse Code), some 18-year old kid in Nevada.\u2026",
      "url": "https://m.ai6yr.org/@ai6yr/116854065230106782",
      "score": 42,
      "comments": 1,
      "created_utc": 1783051532,
      "blurb": "Interesting, just contacted the youngest person I've ever talked to on CW (Morse Code), some 18-year old kid in Nevada. \ud83e\udd14 Usually, I'm the youngster, lol. (I kid you not... have had \"I'm 99 years old\" or \"I'm 100 years\u2026"
    },
    {
      "id": "mastodon_116853165657685947",
      "source": "Mastodon #amateurradio",
      "title": "Looking to get my #AmateurRadio license. Is there anything I should know jumping in? I can consistently pass the\u2026",
      "url": "https://m.alittlenook.net/@trashpanda/116853163471132575",
      "score": 24,
      "comments": 7,
      "created_utc": 1783037772,
      "blurb": "Looking to get my #AmateurRadio license. Is there anything I should know jumping in? I can consistently pass the practice tests on HamExam. Is it worth it to go straight for general? Also, is it worth it to get a #GMRS\u2026"
    },
    {
      "id": "mastodon_116850653791611901",
      "source": "Mastodon #amateurradio",
      "title": "Highlights from our high-altitude balloon flight OH3HAB #9. The weather conditions at different altitudes varied\u2026",
      "url": "https://mastodon.online/@mikaelnou/116850653659176387",
      "score": 12,
      "comments": 0,
      "created_utc": 1782999476,
      "blurb": "Highlights from our high-altitude balloon flight OH3HAB #9. The weather conditions at different altitudes varied heavily: from tiny snowflakes to rain and then back to sunshine! Flight landing spot was perfect: right\u2026"
    },
    {
      "id": "mastodon_116850463548597268",
      "source": "Mastodon #amateurradio",
      "title": "Another surprise in the mailbox!!! This one took 3 years to get to me too!! \ud83d\udc40\ud83e\udd14 #hamradio #amateurradio",
      "url": "https://mastodon.social/@ChrisHolladay/116850463548597268",
      "score": 7,
      "comments": 2,
      "created_utc": 1782996575,
      "blurb": "Another surprise in the mailbox!!! This one took 3 years to get to me too!! \ud83d\udc40\ud83e\udd14 #hamradio #amateurradio"
    },
    {
      "id": "mastodon_116852527531027734",
      "source": "Mastodon #amateurradio",
      "title": "Rather then buy another radio for use as a permanently powered bench radio, I resurrected an old Zares 2m handheld.\u2026",
      "url": "https://mastodon.social/@gmoretti/116852527531027734",
      "score": 8,
      "comments": 1,
      "created_utc": 1783028069,
      "blurb": "Rather then buy another radio for use as a permanently powered bench radio, I resurrected an old Zares 2m handheld. Cracking open the battery compartment revealed four 1.2V NiCd so the radio needs a 6V supply. Wanting\u2026"
    },
    {
      "id": "mastodon_116852212404339000",
      "source": "Mastodon #amateurradio",
      "title": "For Canada Day, I took my #AmateurRadio on a POTA Rover. I originally planned to activate 5 National Historic Sites on\u2026",
      "url": "https://mastodon.futurelab.social/@admin/116852212036666933",
      "score": 9,
      "comments": 0,
      "created_utc": 1783023254,
      "blurb": "For Canada Day, I took my #AmateurRadio on a POTA Rover. I originally planned to activate 5 National Historic Sites on my bike, but when I finished that and went home for lunch (and charge batteries), I couldn't help\u2026"
    },
    {
      "id": "mastodon_116852335686704650",
      "source": "Mastodon #amateurradio",
      "title": "Inflatable #HF vertical. Very cool, and very inexpensive. Anyone here use one of these?\u2026",
      "url": "https://federation.network/notes/ao7jg1idtmay0167",
      "score": 3,
      "comments": 2,
      "created_utc": 1783025141,
      "blurb": "Inflatable #HF vertical. Very cool, and very inexpensive. Anyone here use one of these? https://www.youtube.com/watch?v=eOI344BxrlU #AmateurRadio #HamRadio"
    },
    {
      "id": "mastodon_116851390616036663",
      "source": "Mastodon #hamradio",
      "title": "Will it be worth it to go to a summit this weekend for the VHF contest? I suspect with the 4th of July holiday there\u2026",
      "url": "https://mastodon.radio/@ham_bitious/116851390342846897",
      "score": 4,
      "comments": 1,
      "created_utc": 1783010716,
      "blurb": "Will it be worth it to go to a summit this weekend for the VHF contest? I suspect with the 4th of July holiday there won't be many ops on the air. #hamRadio #vhf #hamR #sota"
    },
    {
      "id": "mastodon_116847004414435908",
      "source": "Mastodon #amateurradio",
      "title": "I got an power amplifier at the flea market at Friedrichshafen. Seems to be working fine. The PTT circuit is a little\u2026",
      "url": "https://social.darc.de/@DF1CN/116847004326633360",
      "score": 4,
      "comments": 0,
      "created_utc": 1782943791,
      "blurb": "I got an power amplifier at the flea market at Friedrichshafen. Seems to be working fine. The PTT circuit is a little bit too powerful for my radio to handle. Looking around my parts I found a Mosfet and an optocoupler\u2026"
    },
    {
      "id": "mastodon_116852305918279523",
      "source": "Mastodon #hamradio",
      "title": "Showing it off juuust a bit. #flipperzero #morsecode #cw #telegraphy #hamradio",
      "url": "https://mastodon.radio/@yo3gnd/116852305641904353",
      "score": 3,
      "comments": 0,
      "created_utc": 1783024683,
      "blurb": "Showing it off juuust a bit. #flipperzero #morsecode #cw #telegraphy #hamradio"
    },
    {
      "id": "mastodon_116852292741143891",
      "source": "Mastodon #sota",
      "title": "#SOTA summit \u2116 734/1000: Hoch Dukan 3063 m (https://sotl.as/summits/HB/GR-177) with Christian HB9GIN \u2013 first activation\u2026",
      "url": "https://mastodon.radio/@hb9dqm/116852292443021077",
      "score": 3,
      "comments": 0,
      "created_utc": 1783024482,
      "blurb": "#SOTA summit \u2116 734/1000: Hoch Dukan 3063 m (https://sotl.as/summits/HB/GR-177) with Christian HB9GIN \u2013 first activation for him, and lots of summit-to-summit QSOs on 2m. This summit has extensive (and somewhat tedious)\u2026"
    },
    {
      "id": "rss_6f3ddd504a79",
      "source": "QRZ Forums",
      "title": "Sussex NJ; SCARC Hamfest Sunday July 12, 2026",
      "url": "https://forums.qrz.com/index.php?threads/sussex-nj-scarc-hamfest-sunday-july-12-2026.992921/",
      "score": 0,
      "comments": 0,
      "created_utc": 1783080346,
      "blurb": ""
    },
    {
      "id": "rss_7c321e453f10",
      "source": "QRZ Forums",
      "title": "The Communicator: July - August 2026",
      "url": "https://forums.qrz.com/index.php?threads/the-communicator-july-august-2026.996146/",
      "score": 0,
      "comments": 0,
      "created_utc": 1783050193,
      "blurb": ""
    },
    {
      "id": "rss_672f67ad464d",
      "source": "QRZ Forums",
      "title": "VJ2L, Lord Howe Is.",
      "url": "https://forums.qrz.com/index.php?threads/vj2l-lord-howe-is.990346/",
      "score": 0,
      "comments": 0,
      "created_utc": 1783044017,
      "blurb": ""
    },
    {
      "id": "rss_875db6f8360e",
      "source": "QRZ Forums",
      "title": "KHam radio on shortwave",
      "url": "https://forums.qrz.com/index.php?threads/kham-radio-on-shortwave.996118/",
      "score": 0,
      "comments": 0,
      "created_utc": 1783038020,
      "blurb": ""
    },
    {
      "id": "rss_6fa6dc2be734",
      "source": "QRZ Forums",
      "title": "Freedom on the Air Special Tiles Event",
      "url": "https://forums.qrz.com/index.php?threads/freedom-on-the-air-special-tiles-event.996115/",
      "score": 0,
      "comments": 0,
      "created_utc": 1783024623,
      "blurb": ""
    },
    {
      "id": "rss_0894b1965cd6",
      "source": "QRZ Forums",
      "title": "why was my post moved?",
      "url": "https://forums.qrz.com/index.php?threads/why-was-my-post-moved.996110/",
      "score": 0,
      "comments": 0,
      "created_utc": 1783019274,
      "blurb": ""
    },
    {
      "id": "rss_e890c881fd4e",
      "source": "QRZ Forums",
      "title": "Slidell LA EOC Hamfest - Sept 4-5",
      "url": "https://forums.qrz.com/index.php?threads/slidell-la-eoc-hamfest-sept-4-5.996107/",
      "score": 0,
      "comments": 0,
      "created_utc": 1783017845,
      "blurb": ""
    },
    {
      "id": "rss_1675bcb64837",
      "source": "QRZ Forums",
      "title": "Users can delete posts?",
      "url": "https://forums.qrz.com/index.php?threads/users-can-delete-posts.996100/",
      "score": 0,
      "comments": 0,
      "created_utc": 1783015827,
      "blurb": ""
    },
    {
      "id": "rss_cb296f63a35f",
      "source": "QRZ Forums",
      "title": "Documentary Tells The Story About An Aging Ham Population",
      "url": "https://forums.qrz.com/index.php?threads/documentary-tells-the-story-about-an-aging-ham-population.991907/",
      "score": 0,
      "comments": 0,
      "created_utc": 1783015739,
      "blurb": ""
    },
    {
      "id": "rss_be325869e602",
      "source": "QRZ Forums",
      "title": "SK PE0SHF - Cor",
      "url": "https://forums.qrz.com/index.php?threads/sk-pe0shf-cor.996104/",
      "score": 0,
      "comments": 0,
      "created_utc": 1783015241,
      "blurb": ""
    }
  ],
  "trends": [
    {
      "term": "hamradio2026",
      "recent_mentions": 3,
      "baseline_mentions": 0,
      "velocity": 3.0,
      "is_new": true
    },
    {
      "term": "SK  June",
      "recent_mentions": 3,
      "baseline_mentions": 1,
      "velocity": 2.25,
      "is_new": false
    },
    {
      "term": "arrl field",
      "recent_mentions": 3,
      "baseline_mentions": 4,
      "velocity": 1.29,
      "is_new": false
    },
    {
      "term": "Morse Code",
      "recent_mentions": 3,
      "baseline_mentions": 4,
      "velocity": 1.29,
      "is_new": false
    }
  ],
  "competitive": [
    {
      "id": "youtube_fM8khkP-k5I",
      "title": "\u041c\u0435\u0448\u0442\u0430\u0441\u0442\u0438\u043a: \u0438\u043d\u0442\u0435\u0440\u043d\u0435\u0442 \u043a\u043e\u043d\u0446\u0430 \u0441\u0432\u0435\u0442\u0430",
      "channel": "\u0428\u0423\u041c",
      "url": "https://www.youtube.com/watch?v=fM8khkP-k5I",
      "views": 1392223,
      "comments": 1345,
      "published": "2026-06-29T11:15:58Z"
    },
    {
      "id": "youtube_5mV0PONjo0E",
      "title": "ONE ANTENNA SHIELDED NINE HOUSES FOR TWENTY YEARS \u26a1\ud83d\udce1\ud83c\udfe0",
      "channel": "Warm Heart Chronicles",
      "url": "https://www.youtube.com/watch?v=5mV0PONjo0E",
      "views": 503242,
      "comments": 86,
      "published": "2026-06-28T01:00:17Z"
    },
    {
      "id": "youtube_ZNh6hTiW5-4",
      "title": "\u0421\u0432\u044f\u0437\u044c \u0431\u0435\u0437 \u0438\u043d\u0442\u0435\u0440\u043d\u0435\u0442\u0430 \u0447\u0435\u0440\u0435\u0437 \u0440\u0430\u0434\u0438\u043e\u0441\u0442\u0430\u043d\u0446\u0438\u0438\u0438 VGC VR-N76",
      "channel": "OKHamRadio",
      "url": "https://www.youtube.com/watch?v=ZNh6hTiW5-4",
      "views": 295624,
      "comments": 706,
      "published": "2026-06-25T21:30:36Z"
    },
    {
      "id": "youtube_pzJpLgylldg",
      "title": "Morse code training #morsecode #hamradio #hobby #practice #train",
      "channel": "Hobby Steve",
      "url": "https://www.youtube.com/watch?v=pzJpLgylldg",
      "views": 106216,
      "comments": 27,
      "published": "2026-06-24T00:29:27Z"
    },
    {
      "id": "youtube_CGWts6YkMbs",
      "title": "Bluetooth Speaker Restoration and Upgrade\ud83e\udd2f part 3 #repair #upgrade #diy",
      "channel": "ELECRAFT",
      "url": "https://www.youtube.com/watch?v=CGWts6YkMbs",
      "views": 83395,
      "comments": 207,
      "published": "2026-06-24T15:35:35Z"
    },
    {
      "id": "youtube_7PKgiDDJSak",
      "title": "The DX launcher is no joke!! @ray_w2re #hobby #hamradio #hamradiolife #antenna #radiooperator",
      "channel": "Hobby Steve",
      "url": "https://www.youtube.com/watch?v=7PKgiDDJSak",
      "views": 66485,
      "comments": 26,
      "published": "2026-06-26T23:26:39Z"
    },
    {
      "id": "youtube_1CM1zxf1g2U",
      "title": "Pangmalakasang Radio! Abot Hanggang Korea?!",
      "channel": "Kuya Odeng",
      "url": "https://www.youtube.com/watch?v=1CM1zxf1g2U",
      "views": 63219,
      "comments": 103,
      "published": "2026-06-22T07:50:10Z"
    },
    {
      "id": "youtube_idlEiWRnSd0",
      "title": "Long Wave radio era end with FM Radio 4 switch-off (UK) 27/Jun/2026",
      "channel": "Mark 1333",
      "url": "https://www.youtube.com/watch?v=idlEiWRnSd0",
      "views": 54372,
      "comments": 376,
      "published": "2026-06-27T13:52:44Z"
    },
    {
      "id": "youtube_-mhtBMsukp4",
      "title": "This tiny solar radio could be your ultimate backup! \u26a1#KMJB #SolarRadio",
      "channel": "KMJB",
      "url": "https://www.youtube.com/watch?v=-mhtBMsukp4",
      "views": 47053,
      "comments": 9,
      "published": "2026-06-28T09:30:40Z"
    },
    {
      "id": "youtube_fQ0loy5HM6g",
      "title": "HamCube Mini #morsecode #hamradio #train",
      "channel": "Forrest (KI7QCF)",
      "url": "https://www.youtube.com/watch?v=fQ0loy5HM6g",
      "views": 46651,
      "comments": 17,
      "published": "2026-06-26T17:41:24Z"
    },
    {
      "id": "youtube_Qt6hB3S3Nb8",
      "title": "Basketball antenna! #hobby #hamradio #hamradiolife #radiooperator #experement",
      "channel": "Hobby Steve",
      "url": "https://www.youtube.com/watch?v=Qt6hB3S3Nb8",
      "views": 45875,
      "comments": 21,
      "published": "2026-06-20T23:19:30Z"
    },
    {
      "id": "youtube_llJ-uzLdTOo",
      "title": "MESHCORE/MESHTASTIC \u041f\u0420\u041e\u0428\u0418\u0412\u041a\u0410 HELTEC WIRELESS PAPER #\u0440\u0430\u0446\u0438\u044f #meshtastic #meshcore #\u0441\u0432\u044f\u0437\u044c",
      "channel": "\u041e\u041b\u0415\u0413\u041e\u0412\u0418\u0427 \u041d\u0410 \u0421\u0412\u042f\u0417\u0418",
      "url": "https://www.youtube.com/watch?v=llJ-uzLdTOo",
      "views": 41947,
      "comments": 28,
      "published": "2026-06-22T20:20:18Z"
    },
    {
      "id": "youtube__9lHdEULO14",
      "title": "You Can Text Without Cell Service?! #edc #meshtastic #communication",
      "channel": "BattlBox",
      "url": "https://www.youtube.com/watch?v=_9lHdEULO14",
      "views": 37073,
      "comments": 22,
      "published": "2026-06-21T22:00:03Z"
    },
    {
      "id": "youtube_l0HlfNXZLQ4",
      "title": "GME XRS-370 GMRS Radio & GME AE4704B-U GMRS Antenna Review - XRS Connect 4x4 Pack",
      "channel": "NotaRubicon Productions",
      "url": "https://www.youtube.com/watch?v=l0HlfNXZLQ4",
      "views": 27752,
      "comments": 192,
      "published": "2026-06-30T23:32:40Z"
    },
    {
      "id": "youtube_mMaV2PMKn8o",
      "title": "BEST Ham Radio Amazon Prime Day Deals 2026!",
      "channel": "Ham Radio DX",
      "url": "https://www.youtube.com/watch?v=mMaV2PMKn8o",
      "views": 19057,
      "comments": 50,
      "published": "2026-06-23T11:38:29Z"
    },
    {
      "id": "youtube__k508Uti_yE",
      "title": "Attempting To Connect Vintage Computers With Meshtastic",
      "channel": "saveitforparts",
      "url": "https://www.youtube.com/watch?v=_k508Uti_yE",
      "views": 16712,
      "comments": 293,
      "published": "2026-06-24T22:00:07Z"
    },
    {
      "id": "youtube_upTaVFsecaw",
      "title": "The Truth About PL259 vs N-Type Connectors",
      "channel": "DXCommander",
      "url": "https://www.youtube.com/watch?v=upTaVFsecaw",
      "views": 16544,
      "comments": 253,
      "published": "2026-06-19T14:36:04Z"
    },
    {
      "id": "youtube_iv32l1FdI0o",
      "title": "Forget the Antenna Analyzer! Do This Instead",
      "channel": "KB9VBR Antennas",
      "url": "https://www.youtube.com/watch?v=iv32l1FdI0o",
      "views": 16146,
      "comments": 98,
      "published": "2026-06-24T20:30:14Z"
    },
    {
      "id": "youtube_h21FP8OM2mU",
      "title": "Seeed Studio Sensecap P1 #meshtastic #lora",
      "channel": "Valleytech Custom Solutions",
      "url": "https://www.youtube.com/watch?v=h21FP8OM2mU",
      "views": 16107,
      "comments": 56,
      "published": "2026-06-23T19:14:52Z"
    },
    {
      "id": "youtube_bJTiILHDfSI",
      "title": "BBC Longwave Is Gone. What Have We Lost?",
      "channel": "Real Ham Radio",
      "url": "https://www.youtube.com/watch?v=bJTiILHDfSI",
      "views": 16102,
      "comments": 174,
      "published": "2026-06-27T06:02:25Z"
    },
    {
      "id": "youtube_A_URPjSESNU",
      "title": "Prime Day 2026",
      "channel": "Temporarily Offline",
      "url": "https://www.youtube.com/watch?v=A_URPjSESNU",
      "views": 15736,
      "comments": 2102,
      "published": "2026-06-23T05:00:37Z"
    },
    {
      "id": "youtube_9wERtkVoCu4",
      "title": "Ai - Concept Video  (Not Real )",
      "channel": "M0FXB HamTech - World of Hobby Radio  Tech Gadgets",
      "url": "https://www.youtube.com/watch?v=9wERtkVoCu4",
      "views": 13275,
      "comments": 3,
      "published": "2026-06-23T21:50:08Z"
    },
    {
      "id": "youtube_lXYChAgxYxM",
      "title": "\u0410\u041d\u0422\u0415\u041d\u041d\u0410 MOXON 868 \u041c\u0413\u0446 \u0417\u0410 15 \u0421\u0415\u041a\u0423\u041d\u0414 #meshtastic #meshcore #reticulum #\u0440\u0430\u0446\u0438\u044f #\u0430\u043d\u0442\u0435\u043d\u043d\u0430",
      "channel": "\u041e\u041b\u0415\u0413\u041e\u0412\u0418\u0427 \u041d\u0410 \u0421\u0412\u042f\u0417\u0418",
      "url": "https://www.youtube.com/watch?v=lXYChAgxYxM",
      "views": 12286,
      "comments": 12,
      "published": "2026-06-28T20:11:24Z"
    },
    {
      "id": "youtube_JWBdXkN5zP4",
      "title": "\u041a\u0430\u043a \u043b\u0435\u0433\u043a\u043e \u0443\u0432\u0435\u043b\u0438\u0447\u0438\u0442\u044c \u0434\u0430\u043b\u044c\u043d\u043e\u0441\u0442\u044c #Meshcore #Meshtastic",
      "channel": "RAZA",
      "url": "https://www.youtube.com/watch?v=JWBdXkN5zP4",
      "views": 12070,
      "comments": 20,
      "published": "2026-06-27T20:12:29Z"
    },
    {
      "id": "youtube_yAmINEghCOc",
      "title": "A $35 Solar Mesh Node Anyone Can Build: The People\u2019s Repeater",
      "channel": "Black Flag Civilian",
      "url": "https://www.youtube.com/watch?v=yAmINEghCOc",
      "views": 11775,
      "comments": 154,
      "published": "2026-07-01T16:56:06Z"
    },
    {
      "id": "youtube_AJERyIUmisI",
      "title": "Build Your Own Off-Grid Network Right Now With MeshCore",
      "channel": "Ham Radio Crash Course",
      "url": "https://www.youtube.com/watch?v=AJERyIUmisI",
      "views": 9188,
      "comments": 68,
      "published": "2026-06-30T17:00:06Z"
    },
    {
      "id": "youtube_t9kvinjMshI",
      "title": "FTX-1\u304c\u30e1\u30fc\u30ab\u30fc\u4fee\u7406\u304b\u3089\u623b\u3063\u3066\u304d\u307e\u3057\u305f\u3002",
      "channel": "\u305f\u304f\u3066\u308c\u3002",
      "url": "https://www.youtube.com/watch?v=t9kvinjMshI",
      "views": 7591,
      "comments": 62,
      "published": "2026-06-29T10:00:06Z"
    },
    {
      "id": "youtube_tc0yTkOVTiU",
      "title": "Did Dayton Hamvention Take it All Outta Me?",
      "channel": "Temporarily Offline",
      "url": "https://www.youtube.com/watch?v=tc0yTkOVTiU",
      "views": 7181,
      "comments": 78,
      "published": "2026-06-19T13:00:07Z"
    },
    {
      "id": "youtube_ocfR9LoBfms",
      "title": "Is Your Phone Tracking You? I'm Installing Graphene OS",
      "channel": "Ham Radio 2.0",
      "url": "https://www.youtube.com/watch?v=ocfR9LoBfms",
      "views": 6943,
      "comments": 47,
      "published": "2026-06-25T19:30:07Z"
    },
    {
      "id": "youtube_BNlLlQjS-uA",
      "title": "\u0421\u0432\u044f\u0437\u044c \u043d\u0430 \u0421\u0438\u0411\u0438 \u043f\u043e\u0441\u043b\u0435 9 \u0432\u0435\u0447\u0435\u0440\u0430 \u043b\u0435\u0442\u043e\u043c",
      "channel": "OKHamRadio",
      "url": "https://www.youtube.com/watch?v=BNlLlQjS-uA",
      "views": 5752,
      "comments": 38,
      "published": "2026-06-26T20:25:24Z"
    },
    {
      "id": "youtube__UOkrInvby4",
      "title": "Amateurfunk News - Juli 2026: HAM RADIO, Erdbeben Venezuela und 70 cm",
      "channel": "DL2YMR",
      "url": "https://www.youtube.com/watch?v=_UOkrInvby4",
      "views": 5055,
      "comments": 62,
      "published": "2026-06-29T19:34:51Z"
    },
    {
      "id": "youtube_wXOYJNIOTR4",
      "title": "Ham Radio Breaking News - Some Great Discount Prices on Ham Radio.",
      "channel": "Waters and Stanton",
      "url": "https://www.youtube.com/watch?v=wXOYJNIOTR4",
      "views": 4978,
      "comments": 38,
      "published": "2026-06-19T14:15:43Z"
    },
    {
      "id": "youtube_wBxmIHGi9Xw",
      "title": "Best Accessories for Yaesu FTX-1",
      "channel": "ML&S Martin Lynch and Sons",
      "url": "https://www.youtube.com/watch?v=wBxmIHGi9Xw",
      "views": 4936,
      "comments": 26,
      "published": "2026-06-26T11:00:06Z"
    },
    {
      "id": "youtube_lFpSW3wCLbQ",
      "title": "\u00c1i C\u00e1c Audio S\u1ed1 532 - ga Tokyo (Tokyo Station), ph\u00eda Yaesu/Marunouchi",
      "channel": "\u00c1i C\u00e1c Audio",
      "url": "https://www.youtube.com/watch?v=lFpSW3wCLbQ",
      "views": 4932,
      "comments": 0,
      "published": "2026-06-30T12:19:46Z"
    },
    {
      "id": "youtube_lAjYOpFeD6w",
      "title": "Ham Radio live S1E3",
      "channel": "DL2YMR",
      "url": "https://www.youtube.com/watch?v=lAjYOpFeD6w",
      "views": 4863,
      "comments": 48,
      "published": "2026-06-26T10:35:37Z"
    },
    {
      "id": "youtube_npTGj5o-_B4",
      "title": "HAM RADIO 2026: Warum sich Friedrichshafen diesmal besonders lohnt",
      "channel": "DL2YMR",
      "url": "https://www.youtube.com/watch?v=npTGj5o-_B4",
      "views": 4333,
      "comments": 64,
      "published": "2026-06-19T14:00:18Z"
    },
    {
      "id": "youtube_OFfZahFxbh4",
      "title": "2E0ZDJ in the Garage",
      "channel": "M0FXB HamTech - World of Hobby Radio  Tech Gadgets",
      "url": "https://www.youtube.com/watch?v=OFfZahFxbh4",
      "views": 4296,
      "comments": 4,
      "published": "2026-06-26T12:48:53Z"
    },
    {
      "id": "youtube_JtdHKnoZAGg",
      "title": "Ham Radio 2026: Eindr\u00fccke",
      "channel": "FUNKFIEBER",
      "url": "https://www.youtube.com/watch?v=JtdHKnoZAGg",
      "views": 4240,
      "comments": 29,
      "published": "2026-06-27T07:00:04Z"
    },
    {
      "id": "youtube_fOwnTV25KSE",
      "title": "Xiegu G90: From Unboxing to First HF Contact",
      "channel": "Practical Comms",
      "url": "https://www.youtube.com/watch?v=fOwnTV25KSE",
      "views": 3761,
      "comments": 2,
      "published": "2026-06-28T15:32:57Z"
    },
    {
      "id": "youtube_6gl_Xx6Ns9U",
      "title": "HANDY YAESU FT411 REPARACION",
      "channel": "David Lightman",
      "url": "https://www.youtube.com/watch?v=6gl_Xx6Ns9U",
      "views": 3734,
      "comments": 71,
      "published": "2026-06-26T19:17:26Z"
    },
    {
      "id": "youtube_NErxn-Eo3EQ",
      "title": "Is Ham Radio Becoming a Video Game? #hamradio",
      "channel": "Ham Radio Perspectives",
      "url": "https://www.youtube.com/watch?v=NErxn-Eo3EQ",
      "views": 3405,
      "comments": 123,
      "published": "2026-06-25T16:58:56Z"
    },
    {
      "id": "youtube_EWm8DUkcMXM",
      "title": "QRP from my garden IC705 + MC-20 MLA",
      "channel": "OM0ET",
      "url": "https://www.youtube.com/watch?v=EWm8DUkcMXM",
      "views": 3402,
      "comments": 16,
      "published": "2026-06-29T07:08:03Z"
    },
    {
      "id": "youtube_FMQcruL5_6c",
      "title": "HAM RADIO 2026 \u2013 Unsere Highlights",
      "channel": "Lutz-Electronics HB9NBG und HB9FZC",
      "url": "https://www.youtube.com/watch?v=FMQcruL5_6c",
      "views": 3356,
      "comments": 7,
      "published": "2026-06-30T14:57:52Z"
    },
    {
      "id": "youtube_u4JoQo3CJZ0",
      "title": "#\u30bf\u30af\u30b7\u30fc\u30c9\u30e9\u30a4\u30d0\u30fc\uff03\u516b\u91cd\u6d32\uff03\u65b0\u5e79\u7dda\uff03\u3044\u3044\u306d\uff03\u8ee2\u8077",
      "channel": "\u30bf\u30af\u30b7\u30fc\u3067\u6708\u5546100\u4e07\u3092\u76ee\u6307\u3059\u5927\u5b66\u3010\u3057\u3085\u3093\u3011",
      "url": "https://www.youtube.com/watch?v=u4JoQo3CJZ0",
      "views": 3210,
      "comments": 4,
      "published": "2026-06-24T10:45:36Z"
    },
    {
      "id": "youtube_CWZwvAB44dE",
      "title": "BMW ICOM NEXT Firmware Update | Fix ISTA Connection Problems",
      "channel": "BimDoc",
      "url": "https://www.youtube.com/watch?v=CWZwvAB44dE",
      "views": 3115,
      "comments": 42,
      "published": "2026-06-30T06:31:50Z"
    },
    {
      "id": "youtube_mYfXb3m8kDE",
      "title": "Aether sdr Flex Radio",
      "channel": "M0FXB HamTech - World of Hobby Radio  Tech Gadgets",
      "url": "https://www.youtube.com/watch?v=mYfXb3m8kDE",
      "views": 2884,
      "comments": 3,
      "published": "2026-06-21T14:10:18Z"
    },
    {
      "id": "youtube_oy0ccVj7K4c",
      "title": "The SharkRF \"M1KE\" Is POLLUTING Ham Radio!!!",
      "channel": "HamRadioConcepts",
      "url": "https://www.youtube.com/watch?v=oy0ccVj7K4c",
      "views": 2744,
      "comments": 88,
      "published": "2026-06-25T22:00:28Z"
    },
    {
      "id": "youtube_kDxVm38hDU4",
      "title": "POTA with the Kiddos at Lake Livingston State Park!!",
      "channel": "The Ham Radio Chick",
      "url": "https://www.youtube.com/watch?v=kDxVm38hDU4",
      "views": 2703,
      "comments": 26,
      "published": "2026-06-20T14:12:04Z"
    },
    {
      "id": "youtube_CXZTbUy2bJY",
      "title": "Ham Radio Friedrichshafen 2026 // Gem\u00fctlich durch die Hallen - A leisurely stroll through the halls",
      "channel": "AlpineRadioWaves",
      "url": "https://www.youtube.com/watch?v=CXZTbUy2bJY",
      "views": 2314,
      "comments": 10,
      "published": "2026-06-27T04:33:56Z"
    },
    {
      "id": "youtube_SdS54IDYdJg",
      "title": "HAM RADIO 2026 Friedrichshafen - Icom X-026",
      "channel": "sq7bce",
      "url": "https://www.youtube.com/watch?v=SdS54IDYdJg",
      "views": 2301,
      "comments": 13,
      "published": "2026-06-29T14:09:55Z"
    },
    {
      "id": "youtube_fg3-TRMNllw",
      "title": "ICOM IC 7300 liberaci\u00f3n total",
      "channel": "HAL(ON LU7DGL",
      "url": "https://www.youtube.com/watch?v=fg3-TRMNllw",
      "views": 2267,
      "comments": 44,
      "published": "2026-06-30T18:27:06Z"
    }
  ]
}